Metadata-Version: 2.1
Name: botasaurus_proxy_authentication
Version: 1.0.4
Summary: Proxy Server with support for SSL, proxy authentication and upstream proxy.
Home-page: https://github.com/omkarcloud/botasaurus-proxy-authentication
Author: Chetan Jain
Author-email: chetan@omkar.cloud
License: MIT
Keywords: seleniumwire proxy authentication,proxy authentication
Classifier: Development Status :: 5 - Production/Stable
Classifier: Topic :: Software Development :: Testing
Classifier: Topic :: System :: Installation/Setup
Classifier: Topic :: Software Development :: Libraries :: Python Modules
Classifier: License :: OSI Approved :: MIT License
Classifier: Programming Language :: Python :: 3
Classifier: Programming Language :: Python :: 3.6
Classifier: Programming Language :: Python :: 3.7
Classifier: Programming Language :: Python :: 3.8
Classifier: Programming Language :: Python :: 3.9
Classifier: Programming Language :: Python :: 3.10
Requires-Python: >=3.6
License-File: LICENSE
